mlflow_go_backend/__init__.py
mlflow_go_backend/cli.py
mlflow_go_backend/lib.py
mlflow_go_backend/libmlflow-go-backend.dylib
mlflow_go_backend/libmlflow-go-backend.h
mlflow_go_backend/server.py
mlflow_go_backend/store/__init__.py
mlflow_go_backend/store/_service_proxy.py
mlflow_go_backend/store/model_registry.py
mlflow_go_backend/store/tracking.py
mlflow_go_backend-0.2.2.dist-info/licenses/LICENSE
mlflow_go_backend-0.2.2.dist-info/METADATA
mlflow_go_backend-0.2.2.dist-info/WHEEL
mlflow_go_backend-0.2.2.dist-info/entry_points.txt
mlflow_go_backend-0.2.2.dist-info/top_level.txt
mlflow_go_backend-0.2.2.dist-info/RECORD
