Metadata-Version: 2.4
Name: mlflow-go-backend
Version: 0.2.2
Summary: MLflow is an open source platform for the complete machine learning lifecycle
Maintainer-email: Databricks <mlflow-oss-maintainers@googlegroups.com>
License:                                  Apache License
Project-URL: homepage, https://mlflow.org
Project-URL: issues, https://github.com/mlflow/mlflow-go-backend/issues
Project-URL: documentation, https://mlflow.org/docs/latest/index.html
Project-URL: repository, https://github.com/mlflow/mlflow-go-backend
Keywords: mlflow,go,golang,ai,databricks
Classifier: Development Status :: 5 - Production/Stable
Classifier: Intended Audience :: Developers
Classifier: Intended Audience :: End Users/Desktop
Classifier: Intended Audience :: Science/Research
Classifier: Intended Audience :: Information Technology
Classifier: Topic :: Scientific/Engineering :: Artificial Intelligence
Classifier: Topic :: Software Development :: Libraries :: Python Modules
Classifier: License :: OSI Approved :: Apache Software License
Classifier: Operating System :: OS Independent
Classifier: Programming Language :: Python :: 3.9
Requires-Python: >=3.9
License-File: LICENSE
Requires-Dist: cffi>=1.17.1
Requires-Dist: mlflow>=2.19.0
Requires-Dist: psycopg2-binary>=2.9.9
Dynamic: license-file
